agntsmth_core/__init__.py
agntsmth_core/core/__init__.py
agntsmth_core/core/agnts/__init__.py
agntsmth_core/core/agnts/agnt_factory.py
agntsmth_core/core/agnts/agnt_state.py
agntsmth_core/core/agnts/agnt_utls.py
agntsmth_core/core/data/__init__.py
agntsmth_core/core/data/chroma_client.py
agntsmth_core/core/prompts/__init__.py
agntsmth_core/core/prompts/sys_prompts.py
agntsmth_core/core/tools/__init__.py
agntsmth_core/core/tools/context_retrieval.py
agntsmth_core/core/tools/dotnet.py
agntsmth_core/core/tools/io.py
agntsmth_core/core/tools/map_yml_to_json_tool.py
agntsmth_core/core/tools/mermaid.py
agntsmth_core/core/tools/sh.py
agntsmth_core/core/utls/__init__.py
agntsmth_core/core/utls/chroma_utls.py
agntsmth_core/core/utls/config_loader.py
agntsmth_core/core/utls/env.py
agntsmth_core/core/utls/hash.py
agntsmth_core/core/utls/io.py
agntsmth_core/core/utls/logger_utls.py
agntsmth_core/core/utls/model_factory.py
agntsmth_core/core/utls/retriever_factory.py
agntsmth_core/core/utls/sh.py
agntsmth_core/core/workflows/__init__.py
agntsmth_core/core/workflows/builder.py
agntsmth_core/vectors/__init__.py
agntsmth_core/vectors/embedding_utls.py
agntsmth_core-0.2.0.dist-info/LICENSE
agntsmth_core-0.2.0.dist-info/METADATA
agntsmth_core-0.2.0.dist-info/WHEEL
agntsmth_core-0.2.0.dist-info/top_level.txt
agntsmth_core-0.2.0.dist-info/RECORD
